resume_parser_upd/__init__.py
resume_parser_upd/constants.py
resume_parser_upd/resumeparse.py
resume_parser_upd-0.8.dist-info/LICENCE.txt
resume_parser_upd-0.8.dist-info/METADATA
resume_parser_upd-0.8.dist-info/WHEEL
resume_parser_upd-0.8.dist-info/top_level.txt
resume_parser_upd-0.8.dist-info/RECORD
