Metadata-Version: 2.1
Name: resume-parser-upd
Version: 0.8
Summary: A resume parser used for extracting information from resumes
Home-page: https://github.com/kbrajwani/resume_parser
Author: DavlatyorSulaymon
Author-email: d.s.olimjanov@gmail.com
License: MIT
Keywords: resume,parser,cv
Platform: UNKNOWN
Classifier: Development Status :: 3 - Alpha
Classifier: Intended Audience :: Developers
Classifier: Topic :: Software Development :: Build Tools
Classifier: License :: OSI Approved :: MIT License
Classifier: Programming Language :: Python :: 3
Classifier: Programming Language :: Python :: 3.4
Classifier: Programming Language :: Python :: 3.5
Classifier: Programming Language :: Python :: 3.6
Requires-Dist: docx2txt (>=0.8)
Requires-Dist: nltk (>=3.5)
Requires-Dist: numpy (>=1.19.1)
Requires-Dist: pandas (>=1.1.0)
Requires-Dist: pdfminer.six (>=20200517)
Requires-Dist: pdfplumber (>=0.5.23)
Requires-Dist: phonenumbers (>=8.12.7)
Requires-Dist: spacy (>=2.3.2)
Requires-Dist: stemming (>=1.0.1)
Requires-Dist: tika (>=1.24)
